{"sectionId":"315","sectionName":"315","stadiumId":"whitesox","totalSeats":40,"totalRows":5,"rows":[{"rowNumber":"1","sectionId":"315","seatCount":8,"elevation":37.5,"depth":97.8,"rowSpacing":36,"seats":[{"id":"whitesox-315-1-1","sectionId":"315","row":"1","seatNumber":"1","position3D":{"x":-28.950819405446758,"y":-93.4167546843349,"z":37.5},"elevation":37.5,"distanceFromHomeplate":97.8,"angle":-17.21875,"facing":162.78125,"seatType":"aisle","hasArmrests":true,"cupHolders":true,"viewQuality":"good","accessibility":{"wheelchairAccessible":false,"companionSeat":false,"requiresStairs":false,"elevatorAccess":false},"covered":true,"overhangHeight":20},{"id":"whitesox-315-1-2","sectionId":"315","row":"1","seatNumber":"2","position3D":{"x":-28.195810538340133,"y":-93.64740395807044,"z":37.5},"elevation":37.5,"distanceFromHomeplate":97.8,"angle":-16.756249999999998,"facing":163.24375,"seatType":"standard","hasArmrests":true,"cupHolders":true,"viewQuality":"good","accessibility":{"wheelchairAccessible":false,"companionSeat":false,"requiresStairs":false,"elevatorAccess":false},"covered":true,"overhangHeight":20},{"id":"whitesox-315-1-3","sectionId":"315","row":"1","seatNumber":"3","position3D":{"x":-27.43896445432048,"y":-93.87195124037072,"z":37.5},"elevation":37.5,"distanceFromHomeplate":97.8,"angle":-16.29375,"facing":163.70625,"seatType":"standard","hasArmrests":true,"cupHolders":true,"viewQuality":"good","accessibility":{"wheelchairAccessible":false,"companionSeat":false,"requiresStairs":false,"elevatorAccess":false},"covered":true,"overhangHeight":20},{"id":"whitesox-315-1-4","sectionId":"315","row":"1","seatNumber":"4","position3D":{"x":-26.68033046888535,"y":-94.09038189991082,"z":37.5},"elevation":37.5,"distanceFromHomeplate":97.8,"angle":-15.831249999999999,"facing":164.16875,"seatType":"standard","hasArmrests":true,"cupHolders":true,"viewQuality":"good","accessibility":{"wheelchairAccessible":false,"companionSeat":false,"requiresStairs":false,"elevatorAccess":false},"covered":true,"overhangHeight":20},{"id":"whitesox-315-1-5","sectionId":"315","row":"1","seatNumber":"5","position3D":{"x":-25.919958014030563,"y":-94.30268170392023,"z":37.5},"elevation":37.5,"distanceFromHomeplate":97.8,"angle":-15.368749999999999,"facing":164.63125,"seatType":"standard","hasArmrests":true,"cupHolders":true,"viewQuality":"good","accessibility":{"wheelchairAccessible":false,"companionSeat":false,"requiresStairs":false,"elevatorAccess":false},"covered":true,"overhangHeight":20},{"id":"whitesox-315-1-6","sectionId":"315","row":"1","seatNumber":"6","position3D":{"x":-25.157896635029243,"y":-94.50883681911012,"z":37.5},"elevation":37.5,"distanceFromHomeplate":97.8,"angle":-14.90625,"facing":165.09375,"seatType":"standard","hasArmrests":true,"cupHolders":true,"viewQuality":"good","accessibility":{"wheelchairAccessible":false,"companionSeat":false,"requiresStairs":false,"elevatorAccess":false},"covered":true,"overhangHeight":20},{"id":"whitesox-315-1-7","sectionId":"315","row":"1","seatNumber":"7","position3D":{"x":-24.3941959872035,"y":-94.70883381257477,"z":37.5},"elevation":37.5,"distanceFromHomeplate":97.8,"angle":-14.44375,"facing":165.55625,"seatType":"standard","hasArmrests":true,"cupHolders":true,"viewQuality":"good","accessibility":{"wheelchairAccessible":false,"companionSeat":false,"requiresStairs":false,"elevatorAccess":false},"covered":true,"overhangHeight":20},{"id":"whitesox-315-1-8","sectionId":"315","row":"1","seatNumber":"8","position3D":{"x":-23.628905832688957,"y":-94.90265965266683,"z":37.5},"elevation":37.5,"distanceFromHomeplate":97.8,"angle":-13.98125,"facing":166.01875,"seatType":"aisle","hasArmrests":true,"cupHolders":true,"viewQuality":"good","accessibility":{"wheelchairAccessible":false,"companionSeat":false,"requiresStairs":false,"elevatorAccess":false},"covered":true,"overhangHeight":20}],"covered":true,"overhangHeight":20,"hasAisleSeats":false,"wheelchairRow":false},{"rowNumber":"2","sectionId":"315","seatCount":8,"elevation":40,"depth":100.6,"rowSpacing":36,"seats":[{"id":"whitesox-315-2-1","sectionId":"315","row":"2","seatNumber":"1","position3D":{"x":-29.77967722073562,"y":-96.09126299840584,"z":40},"elevation":40,"distanceFromHomeplate":100.6,"angle":-17.21875,"facing":162.78125,"seatType":"aisle","hasArmrests":true,"cupHolders":true,"viewQuality":"good","accessibility":{"wheelchairAccessible":false,"companionSeat":false,"requiresStairs":false,"elevatorAccess":false},"covered":true,"overhangHeight":20},{"id":"whitesox-315-2-2","sectionId":"315","row":"2","seatNumber":"2","position3D":{"x":-29.00305255784271,"y":-96.32851572783115,"z":40},"elevation":40,"distanceFromHomeplate":100.6,"angle":-16.756249999999998,"facing":163.24375,"seatType":"standard","hasArmrests":true,"cupHolders":true,"viewQuality":"good","accessibility":{"wheelchairAccessible":false,"companionSeat":false,"requiresStairs":false,"elevatorAccess":false},"covered":true,"overhangHeight":20},{"id":"whitesox-315-2-3","sectionId":"315","row":"2","seatNumber":"3","position3D":{"x":-28.224538078779553,"y":-96.5594917666799,"z":40},"elevation":40,"distanceFromHomeplate":100.60000000000001,"angle":-16.29375,"facing":163.70625,"seatType":"standard","hasArmrests":true,"cupHolders":true,"viewQuality":"good","accessibility":{"wheelchairAccessible":false,"companionSeat":false,"requiresStairs":false,"elevatorAccess":false},"covered":true,"overhangHeight":20},{"id":"whitesox-315-2-4","sectionId":"315","row":"2","seatNumber":"4","position3D":{"x":-27.444184510939326,"y":-96.78417606473445,"z":40},"elevation":40,"distanceFromHomeplate":100.60000000000001,"angle":-15.831249999999999,"facing":164.16875,"seatType":"standard","hasArmrests":true,"cupHolders":true,"viewQuality":"good","accessibility":{"wheelchairAccessible":false,"companionSeat":false,"requiresStairs":false,"elevatorAccess":false},"covered":true,"overhangHeight":20},{"id":"whitesox-315-2-5","sectionId":"315","row":"2","seatNumber":"5","position3D":{"x":-26.66204270154882,"y":-97.00255398174208,"z":40},"elevation":40,"distanceFromHomeplate":100.60000000000001,"angle":-15.368749999999999,"facing":164.63125,"seatType":"standard","hasArmrests":true,"cupHolders":true,"viewQuality":"good","accessibility":{"wheelchairAccessible":false,"companionSeat":false,"requiresStairs":false,"elevatorAccess":false},"covered":true,"overhangHeight":20},{"id":"whitesox-315-2-6","sectionId":"315","row":"2","seatNumber":"6","position3D":{"x":-25.87816361435523,"y":-97.21461128836889,"z":40},"elevation":40,"distanceFromHomeplate":100.59999999999998,"angle":-14.90625,"facing":165.09375,"seatType":"standard","hasArmrests":true,"cupHolders":true,"viewQuality":"good","accessibility":{"wheelchairAccessible":false,"companionSeat":false,"requiresStairs":false,"elevatorAccess":false},"covered":true,"overhangHeight":20},{"id":"whitesox-315-2-7","sectionId":"315","row":"2","seatNumber":"7","position3D":{"x":-25.09259832630544,"y":-97.420334167127,"z":40},"elevation":40,"distanceFromHomeplate":100.6,"angle":-14.44375,"facing":165.55625,"seatType":"standard","hasArmrests":true,"cupHolders":true,"viewQuality":"good","accessibility":{"wheelchairAccessible":false,"companionSeat":false,"requiresStairs":false,"elevatorAccess":false},"covered":true,"overhangHeight":20},{"id":"whitesox-315-2-8","sectionId":"315","row":"2","seatNumber":"8","position3D":{"x":-24.305398024217883,"y":-97.61970921327487,"z":40},"elevation":40,"distanceFromHomeplate":100.59999999999998,"angle":-13.98125,"facing":166.01875,"seatType":"aisle","hasArmrests":true,"cupHolders":true,"viewQuality":"good","accessibility":{"wheelchairAccessible":false,"companionSeat":false,"requiresStairs":false,"elevatorAccess":false},"covered":true,"overhangHeight":20}],"covered":true,"overhangHeight":20,"hasAisleSeats":false,"wheelchairRow":false},{"rowNumber":"3","sectionId":"315","seatCount":8,"elevation":42.5,"depth":103.4,"rowSpacing":36,"seats":[{"id":"whitesox-315-3-1","sectionId":"315","row":"3","seatNumber":"1","position3D":{"x":-30.608535036024488,"y":-98.76577131247679,"z":42.5},"elevation":42.5,"distanceFromHomeplate":103.4,"angle":-17.21875,"facing":162.78125,"seatType":"aisle","hasArmrests":true,"cupHolders":true,"viewQuality":"good","accessibility":{"wheelchairAccessible":false,"companionSeat":false,"requiresStairs":false,"elevatorAccess":false},"covered":true,"overhangHeight":20},{"id":"whitesox-315-3-2","sectionId":"315","row":"3","seatNumber":"2","position3D":{"x":-29.810294577345296,"y":-99.00962749759186,"z":42.5},"elevation":42.5,"distanceFromHomeplate":103.4,"angle":-16.756249999999998,"facing":163.24375,"seatType":"standard","hasArmrests":true,"cupHolders":true,"viewQuality":"good","accessibility":{"wheelchairAccessible":false,"companionSeat":false,"requiresStairs":false,"elevatorAccess":false},"covered":true,"overhangHeight":20},{"id":"whitesox-315-3-3","sectionId":"315","row":"3","seatNumber":"3","position3D":{"x":-29.01011170323863,"y":-99.24703229298909,"z":42.5},"elevation":42.5,"distanceFromHomeplate":103.4,"angle":-16.29375,"facing":163.70625,"seatType":"standard","hasArmrests":true,"cupHolders":true,"viewQuality":"good","accessibility":{"wheelchairAccessible":false,"companionSeat":false,"requiresStairs":false,"elevatorAccess":false},"covered":true,"overhangHeight":20},{"id":"whitesox-315-3-4","sectionId":"315","row":"3","seatNumber":"4","position3D":{"x":-28.208038552993308,"y":-99.47797022955808,"z":42.5},"elevation":42.5,"distanceFromHomeplate":103.4,"angle":-15.831249999999999,"facing":164.16875,"seatType":"standard","hasArmrests":true,"cupHolders":true,"viewQuality":"good","accessibility":{"wheelchairAccessible":false,"companionSeat":false,"requiresStairs":false,"elevatorAccess":false},"covered":true,"overhangHeight":20},{"id":"whitesox-315-3-5","sectionId":"315","row":"3","seatNumber":"5","position3D":{"x":-27.40412738906708,"y":-99.70242625956394,"z":42.5},"elevation":42.5,"distanceFromHomeplate":103.4,"angle":-15.368749999999999,"facing":164.63125,"seatType":"standard","hasArmrests":true,"cupHolders":true,"viewQuality":"good","accessibility":{"wheelchairAccessible":false,"companionSeat":false,"requiresStairs":false,"elevatorAccess":false},"covered":true,"overhangHeight":20},{"id":"whitesox-315-3-6","sectionId":"315","row":"3","seatNumber":"6","position3D":{"x":-26.598430593681226,"y":-99.92038575762767,"z":42.5},"elevation":42.5,"distanceFromHomeplate":103.39999999999999,"angle":-14.90625,"facing":165.09375,"seatType":"standard","hasArmrests":true,"cupHolders":true,"viewQuality":"good","accessibility":{"wheelchairAccessible":false,"companionSeat":false,"requiresStairs":false,"elevatorAccess":false},"covered":true,"overhangHeight":20},{"id":"whitesox-315-3-7","sectionId":"315","row":"3","seatNumber":"7","position3D":{"x":-25.79100066540738,"y":-100.13183452167925,"z":42.5},"elevation":42.5,"distanceFromHomeplate":103.4,"angle":-14.44375,"facing":165.55625,"seatType":"standard","hasArmrests":true,"cupHolders":true,"viewQuality":"good","accessibility":{"wheelchairAccessible":false,"companionSeat":false,"requiresStairs":false,"elevatorAccess":false},"covered":true,"overhangHeight":20},{"id":"whitesox-315-3-8","sectionId":"315","row":"3","seatNumber":"8","position3D":{"x":-24.981890215746812,"y":-100.33675877388293,"z":42.5},"elevation":42.5,"distanceFromHomeplate":103.39999999999999,"angle":-13.98125,"facing":166.01875,"seatType":"aisle","hasArmrests":true,"cupHolders":true,"viewQuality":"good","accessibility":{"wheelchairAccessible":false,"companionSeat":false,"requiresStairs":false,"elevatorAccess":false},"covered":true,"overhangHeight":20}],"covered":true,"overhangHeight":20,"hasAisleSeats":false,"wheelchairRow":false},{"rowNumber":"4","sectionId":"315","seatCount":8,"elevation":45,"depth":106.2,"rowSpacing":36,"seats":[{"id":"whitesox-315-4-1","sectionId":"315","row":"4","seatNumber":"1","position3D":{"x":-31.43739285131335,"y":-101.44027962654772,"z":45},"elevation":45,"distanceFromHomeplate":106.2,"angle":-17.21875,"facing":162.78125,"seatType":"aisle","hasArmrests":true,"cupHolders":true,"viewQuality":"good","accessibility":{"wheelchairAccessible":false,"companionSeat":false,"requiresStairs":false,"elevatorAccess":false},"covered":true,"overhangHeight":20},{"id":"whitesox-315-4-2","sectionId":"315","row":"4","seatNumber":"2","position3D":{"x":-30.617536596847874,"y":-101.69073926735257,"z":45},"elevation":45,"distanceFromHomeplate":106.2,"angle":-16.756249999999998,"facing":163.24375,"seatType":"standard","hasArmrests":true,"cupHolders":true,"viewQuality":"good","accessibility":{"wheelchairAccessible":false,"companionSeat":false,"requiresStairs":false,"elevatorAccess":false},"covered":true,"overhangHeight":20},{"id":"whitesox-315-4-3","sectionId":"315","row":"4","seatNumber":"3","position3D":{"x":-29.7956853276977,"y":-101.93457281929827,"z":45},"elevation":45,"distanceFromHomeplate":106.20000000000002,"angle":-16.29375,"facing":163.70625,"seatType":"standard","hasArmrests":true,"cupHolders":true,"viewQuality":"good","accessibility":{"wheelchairAccessible":false,"companionSeat":false,"requiresStairs":false,"elevatorAccess":false},"covered":true,"overhangHeight":20},{"id":"whitesox-315-4-4","sectionId":"315","row":"4","seatNumber":"4","position3D":{"x":-28.971892595047283,"y":-102.17176439438171,"z":45},"elevation":45,"distanceFromHomeplate":106.2,"angle":-15.831249999999999,"facing":164.16875,"seatType":"standard","hasArmrests":true,"cupHolders":true,"viewQuality":"good","accessibility":{"wheelchairAccessible":false,"companionSeat":false,"requiresStairs":false,"elevatorAccess":false},"covered":true,"overhangHeight":20},{"id":"whitesox-315-4-5","sectionId":"315","row":"4","seatNumber":"5","position3D":{"x":-28.14621207658534,"y":-102.40229853738578,"z":45},"elevation":45,"distanceFromHomeplate":106.19999999999999,"angle":-15.368749999999999,"facing":164.63125,"seatType":"standard","hasArmrests":true,"cupHolders":true,"viewQuality":"good","accessibility":{"wheelchairAccessible":false,"companionSeat":false,"requiresStairs":false,"elevatorAccess":false},"covered":true,"overhangHeight":20},{"id":"whitesox-315-4-6","sectionId":"315","row":"4","seatNumber":"6","position3D":{"x":-27.318697573007217,"y":-102.62616022688644,"z":45},"elevation":45,"distanceFromHomeplate":106.19999999999999,"angle":-14.90625,"facing":165.09375,"seatType":"standard","hasArmrests":true,"cupHolders":true,"viewQuality":"good","accessibility":{"wheelchairAccessible":false,"companionSeat":false,"requiresStairs":false,"elevatorAccess":false},"covered":true,"overhangHeight":20},{"id":"whitesox-315-4-7","sectionId":"315","row":"4","seatNumber":"7","position3D":{"x":-26.48940300450932,"y":-102.8433348762315,"z":45},"elevation":45,"distanceFromHomeplate":106.2,"angle":-14.44375,"facing":165.55625,"seatType":"standard","hasArmrests":true,"cupHolders":true,"viewQuality":"good","accessibility":{"wheelchairAccessible":false,"companionSeat":false,"requiresStairs":false,"elevatorAccess":false},"covered":true,"overhangHeight":20},{"id":"whitesox-315-4-8","sectionId":"315","row":"4","seatNumber":"8","position3D":{"x":-25.658382407275738,"y":-103.05380833449098,"z":45},"elevation":45,"distanceFromHomeplate":106.2,"angle":-13.98125,"facing":166.01875,"seatType":"aisle","hasArmrests":true,"cupHolders":true,"viewQuality":"good","accessibility":{"wheelchairAccessible":false,"companionSeat":false,"requiresStairs":false,"elevatorAccess":false},"covered":true,"overhangHeight":20}],"covered":true,"overhangHeight":20,"hasAisleSeats":false,"wheelchairRow":false},{"rowNumber":"5","sectionId":"315","seatCount":8,"elevation":47.5,"depth":109,"rowSpacing":36,"seats":[{"id":"whitesox-315-5-1","sectionId":"315","row":"5","seatNumber":"1","position3D":{"x":-32.26625066660221,"y":-104.11478794061865,"z":47.5},"elevation":47.5,"distanceFromHomeplate":109,"angle":-17.21875,"facing":162.78125,"seatType":"aisle","hasArmrests":true,"cupHolders":true,"viewQuality":"good","accessibility":{"wheelchairAccessible":false,"companionSeat":false,"requiresStairs":false,"elevatorAccess":false},"covered":true,"overhangHeight":20},{"id":"whitesox-315-5-2","sectionId":"315","row":"5","seatNumber":"2","position3D":{"x":-31.424778616350455,"y":-104.37185103711327,"z":47.5},"elevation":47.5,"distanceFromHomeplate":109,"angle":-16.756249999999998,"facing":163.24375,"seatType":"standard","hasArmrests":true,"cupHolders":true,"viewQuality":"good","accessibility":{"wheelchairAccessible":false,"companionSeat":false,"requiresStairs":false,"elevatorAccess":false},"covered":true,"overhangHeight":20},{"id":"whitesox-315-5-3","sectionId":"315","row":"5","seatNumber":"3","position3D":{"x":-30.581258952156773,"y":-104.62211334560745,"z":47.5},"elevation":47.5,"distanceFromHomeplate":109.00000000000001,"angle":-16.29375,"facing":163.70625,"seatType":"standard","hasArmrests":true,"cupHolders":true,"viewQuality":"good","accessibility":{"wheelchairAccessible":false,"companionSeat":false,"requiresStairs":false,"elevatorAccess":false},"covered":true,"overhangHeight":20},{"id":"whitesox-315-5-4","sectionId":"315","row":"5","seatNumber":"4","position3D":{"x":-29.73574663710126,"y":-104.86555855920533,"z":47.5},"elevation":47.5,"distanceFromHomeplate":109,"angle":-15.831249999999999,"facing":164.16875,"seatType":"standard","hasArmrests":true,"cupHolders":true,"viewQuality":"good","accessibility":{"wheelchairAccessible":false,"companionSeat":false,"requiresStairs":false,"elevatorAccess":false},"covered":true,"overhangHeight":20},{"id":"whitesox-315-5-5","sectionId":"315","row":"5","seatNumber":"5","position3D":{"x":-28.888296764103593,"y":-105.10217081520763,"z":47.5},"elevation":47.5,"distanceFromHomeplate":109,"angle":-15.368749999999999,"facing":164.63125,"seatType":"standard","hasArmrests":true,"cupHolders":true,"viewQuality":"good","accessibility":{"wheelchairAccessible":false,"companionSeat":false,"requiresStairs":false,"elevatorAccess":false},"covered":true,"overhangHeight":20},{"id":"whitesox-315-5-6","sectionId":"315","row":"5","seatNumber":"6","position3D":{"x":-28.038964552333205,"y":-105.33193469614523,"z":47.5},"elevation":47.5,"distanceFromHomeplate":109,"angle":-14.90625,"facing":165.09375,"seatType":"standard","hasArmrests":true,"cupHolders":true,"viewQuality":"good","accessibility":{"wheelchairAccessible":false,"companionSeat":false,"requiresStairs":false,"elevatorAccess":false},"covered":true,"overhangHeight":20},{"id":"whitesox-315-5-7","sectionId":"315","row":"5","seatNumber":"7","position3D":{"x":-27.187805343611263,"y":-105.55483523078374,"z":47.5},"elevation":47.5,"distanceFromHomeplate":109,"angle":-14.44375,"facing":165.55625,"seatType":"standard","hasArmrests":true,"cupHolders":true,"viewQuality":"good","accessibility":{"wheelchairAccessible":false,"companionSeat":false,"requiresStairs":false,"elevatorAccess":false},"covered":true,"overhangHeight":20},{"id":"whitesox-315-5-8","sectionId":"315","row":"5","seatNumber":"8","position3D":{"x":-26.334874598804667,"y":-105.77085789509903,"z":47.5},"elevation":47.5,"distanceFromHomeplate":109,"angle":-13.98125,"facing":166.01875,"seatType":"aisle","hasArmrests":true,"cupHolders":true,"viewQuality":"good","accessibility":{"wheelchairAccessible":false,"companionSeat":false,"requiresStairs":false,"elevatorAccess":false},"covered":true,"overhangHeight":20}],"covered":true,"overhangHeight":20,"hasAisleSeats":false,"wheelchairRow":false}],"seatDistribution":{"standard":30,"aisle":10,"wheelchair":0,"companion":0,"other":0}}